{"id":1,"name":"AC/DC","hometown":"Sydney","year":1973}
{"id":5,"name":"PVT","hometown":"Sydney","year":1986}
{"id":0,"name":"Led Zeppelin","hometown":"London","year":1968}
{"id":6,"name":"The Rolling Stones","hometown":"London","year":1968}
{"id":7,"name":"The Clash","hometown":"London","year":1968}
{"id":3,"name":"Metallica","hometown":"Los Angeles","year":1981}
{"id":8,"name":"Weezer","hometown":"Los Angeles","year":1993}
{"id":9,"name":"Bad Religion","hometown":"Los Angeles","year":1979}
{"id":4,"name":"The Beatles","hometown":"Liverpool","year":1960}
