{"commitInfo":{"timestamp":1664593833236,"operation":"MERGE","operationParameters":{"predicate":"(m.`dni` = in.`dni`)","matchedPredicates":"[{\"actionType\":\"update\"}]","notMatchedPredicates":"[{\"actionType\":\"insert\"}]"},"readVersion":0,"isBlindAppend":false,"operationMetrics":{"numTargetRowsCopied":"0","numTargetRowsDeleted":"0","numTargetFilesAdded":"1","executionTimeMs":"2109","numTargetRowsInserted":"0","scanTimeMs":"1346","numTargetRowsUpdated":"0","numOutputRows":"0","numSourceRows":"0","numTargetFilesRemoved":"0","rewriteTimeMs":"738"}}}
{"add":{"path":"part-00000-a96d9168-2996-47d5-8eee-fe5fe4d972ac-c000.snappy.parquet","partitionValues":{},"size":462,"modificationTime":1664593833148,"dataChange":true}}
